LICENSE.txt
MANIFEST.in
README
README.rst
setup.cfg
setup.py
tests/__init__.py
tests/test_jquery.py
tw2/__init__.py
tw2.jquery.egg-info/PKG-INFO
tw2.jquery.egg-info/SOURCES.txt
tw2.jquery.egg-info/dependency_links.txt
tw2.jquery.egg-info/entry_points.txt
tw2.jquery.egg-info/namespace_packages.txt
tw2.jquery.egg-info/not-zip-safe
tw2.jquery.egg-info/requires.txt
tw2.jquery.egg-info/top_level.txt
tw2/jquery/__init__.py
tw2/jquery/base.py
tw2/jquery/defaults.py
tw2/jquery/version.py
tw2/jquery/static/jquery/1.3.2/jquery.js
tw2/jquery/static/jquery/1.3.2/jquery.min.js
tw2/jquery/static/jquery/1.4.2/jquery.js
tw2/jquery/static/jquery/1.4.2/jquery.min.js
tw2/jquery/static/jquery/1.4.4/jquery.js
tw2/jquery/static/jquery/1.4.4/jquery.min.js
tw2/jquery/static/jquery/1.6.0/jquery.js
tw2/jquery/static/jquery/1.6.0/jquery.min.js
tw2/jquery/static/jquery/1.6.2/jquery.js
tw2/jquery/static/jquery/1.6.2/jquery.min.js
tw2/jquery/static/jquery/1.7.1/jquery.js
tw2/jquery/static/jquery/1.7.1/jquery.min.js
tw2/jquery/static/jquery/1.8.3/jquery.js
tw2/jquery/static/jquery/1.8.3/jquery.min.js
tw2/jquery/static/jquery/1.9.1/jquery.js
tw2/jquery/static/jquery/1.9.1/jquery.min.js
tw2/jquery/static/jquery/plugins/Jcrop/0.9.8/css/Jcrop.gif
tw2/jquery/static/jquery/plugins/Jcrop/0.9.8/css/jquery.Jcrop.css
tw2/jquery/static/jquery/plugins/Jcrop/0.9.8/js/jquery.Jcrop.js
tw2/jquery/static/jquery/plugins/Jcrop/0.9.8/js/jquery.Jcrop.min.js
tw2/jquery/static/jquery/plugins/nullable/1.0/js/jquery.nullable.js
tw2/jquery/static/jquery/plugins/switchview/1.2/css/jquery.switchview.css
tw2/jquery/static/jquery/plugins/switchview/1.2/js/jquery.switchview.js
tw2/jquery/static/jquery/plugins/switchview/1.2/js/jquery.switchview.min.js