Metadata-Version: 1.1
Name: tw2.jquery
Version: 2.2.0
Summary: toscawidgets2 wrapper for jQuery
Home-page: http://github.com/toscawidgets/tw2.jquery
Author: Joseph Tate
Author-email: jtate@dragonstrider.com
License: MIT
Keywords: toscawidgets.widgets
Platform: UNKNOWN
Classifier: Development Status :: 5 - Production/Stable
Classifier: Environment :: Web Environment
Classifier: Environment :: Web Environment :: ToscaWidgets
Classifier: Topic :: Software Development :: Libraries :: Python Modules
Classifier: Topic :: Software Development :: Widget Sets
Classifier: Intended Audience :: Developers
Classifier: Operating System :: OS Independent
Classifier: Programming Language :: Python
Classifier: Programming Language :: JavaScript
Classifier: License :: OSI Approved :: MIT License
